[
  {
    "timestamp": "2026-05-04T13:15:43.293212+00:00",
    "symbol": "BZ=F",
    "name": "Brent Crude",
    "price": 110.68000030517578
  },
  {
    "timestamp": "2026-05-04T13:15:43.293212+00:00",
    "symbol": "CL=F",
    "name": "WTI Crude",
    "price": 102.91999816894531
  },
  {
    "timestamp": "2026-05-04T13:15:43.293212+00:00",
    "symbol": "NG=F",
    "name": "Natural Gas",
    "price": 2.813999891281128
  },
  {
    "timestamp": "2026-05-04T13:15:43.293212+00:00",
    "symbol": "ITA",
    "name": "Defense ETF",
    "price": 216.27000427246094
  },
  {
    "timestamp": "2026-05-04T13:15:43.293212+00:00",
    "symbol": "SEA",
    "name": "Shipping ETF",
    "price": 17.45599937438965
  },
  {
    "timestamp": "2026-05-04T13:15:43.293212+00:00",
    "symbol": "GSG",
    "name": "Commodity Index",
    "price": 33.88999938964844
  },
  {
    "timestamp": "2026-05-04T13:15:43.293212+00:00",
    "symbol": "^VIX",
    "name": "Volatility Index",
    "price": 17.850000381469727
  }
]